unavoids/__init__.py
unavoids/aggregate.py
unavoids/experiments.py
unavoids/genPrevelanceArrs.py
unavoids/genSimulatedDataSet.py
unavoids/genSimulationNCDFs.py
unavoids/loadAndCleanDoH.py
unavoids/loadAndCleanIDS.py
unavoids/txtToLatex.py
unavoids/unavoids.py
unavoids-1.4.dist-info/METADATA
unavoids-1.4.dist-info/WHEEL
unavoids-1.4.dist-info/top_level.txt
unavoids-1.4.dist-info/RECORD
