Metadata-Version: 2.1
Name: unavoids
Version: 1.4
Summary: UNKNOWN
Home-page: https://github.com/isotlaboratory/UNAVOIDS-Code
Author: Yousef, Waleed A. and Traoré, Issa and Briguglio, William
Author-email: wyousef@uvic.ca
License: GNU GENERAL PUBLIC LICENSE
Platform: UNKNOWN
